sudiptocalculator/__init__.py
sudiptocalculator/calculator.py
sudiptocalculator-0.0.2.dist-info/LICENSE
sudiptocalculator-0.0.2.dist-info/METADATA
sudiptocalculator-0.0.2.dist-info/WHEEL
sudiptocalculator-0.0.2.dist-info/top_level.txt
sudiptocalculator-0.0.2.dist-info/RECORD
