Metadata-Version: 2.1
Name: sudiptocalculator
Version: 0.0.2
Summary: This is a very basic calculator
Author: Sudipto sarker
Author-email: sarkersudipto182@gmail.com
License-File: LICENSE
